{
  "!type": "Card_bs4", 
  "align": "", 
  "backgroundColor": "", 
  "bgColor": "", 
  "borderColor": "", 
  "borderStyle": "", 
  "borderWidth": "", 
  "bottom": "auto", 
  "cached_js": "", 
  "cached_js_script_hash": "d41d8cd98f00b204e9800998ecf8427e", 
  "children": [], 
  "class": "", 
  "color": "", 
  "display": "", 
  "expanded_pmp": null, 
  "fontFamily": "", 
  "fontSize": "", 
  "fontStyle": "", 
  "fontWeight": "", 
  "footerClass": "", 
  "footerStyle": "", 
  "footerValue": "", 
  "header": "Card", 
  "headerClass": "", 
  "headerStyle": "", 
  "headerValue": "", 
  "height": "auto", 
  "hidden": "", 
  "id": "Card1", 
  "imageClass": "", 
  "imageHeight": 60, 
  "imageStyle": "", 
  "imageWidth": 60, 
  "left": 36, 
  "mAll": "", 
  "mBottom": "", 
  "mLeft": "", 
  "mRight": "", 
  "mTop": "", 
  "onclick": "", 
  "onmousedown": "", 
  "onmousemove": "", 
  "onmouseout": "", 
  "onmouseup": "", 
  "onresize": "", 
  "ontouchend": "", 
  "ontouchmove": "", 
  "ontouchstart": "", 
  "pAll": "", 
  "pBottom": "", 
  "pLeft": "", 
  "pRight": "", 
  "pTop": "", 
  "position": "static", 
  "right": "auto", 
  "script": "", 
  "src": "", 
  "style": "", 
  "subtitleClass": "", 
  "subtitleStyle": "", 
  "subtitleValue": "", 
  "textClass": "", 
  "textColor": "", 
  "textStyle": "", 
  "textValue": "This app converts all controls of a Bootstrap 3 or jQuery Mobile project to Bootstrap 4. \nIt does it in place: the project is modified directly. Keep a backup!<br>\n\n<p>The path can also be entered manually. In this case, all projects in the path will be converted.\n\n<p><b>Notes</b>\nAll controls are converted, with the exception of controls which do not exist in Bootstrap 4. \nIn this case, the converter will replace these controls with a simple Container with the same name and dimensions.\n\n<br><p>You'll have to do fixups to your controls after the conversion is done. \nThis utility does not expect to a complete conversion, but it will save you a lot of time\nby producing a new project with all the same controls, with the same ids, text values and positions.\n", 
  "titleClass": "", 
  "titleStyle": "", 
  "titleValue": "", 
  "top": 331, 
  "width": 658
}